LICENSE
MANIFEST.in
README.md
setup.py
src/ea_agents/__init__.py
src/ea_agents/plugins/__init__.py
src/ea_agents/plugins/sikulix/__init__.py
src/ea_agents/plugins/sikulix/agent_sikulix.py
src/ea_agents/plugins/sikulix/bin/SIKULI_VERSION
src/ea_agents/plugins/sikulix/bin/SikuliX-1.1.2-SetupLog.txt
src/ea_agents/plugins/sikulix/bin/sikuli-script.bat
src/ea_agents/plugins/sikulix/bin/sikulix.jar
src/ea_agents/plugins/sikulix/bin/sikulixsetup-1.1.2.jar
src/ea_agents/plugins/sikulix/deps/install.bat
src/extensiveautomation_agent_plugin_sikulix.egg-info/PKG-INFO
src/extensiveautomation_agent_plugin_sikulix.egg-info/SOURCES.txt
src/extensiveautomation_agent_plugin_sikulix.egg-info/dependency_links.txt
src/extensiveautomation_agent_plugin_sikulix.egg-info/requires.txt
src/extensiveautomation_agent_plugin_sikulix.egg-info/top_level.txt